aoc/__init__.py
aoc/helpers.py
aoc/input_handler.py
aoc/input_manager.py
aoc/reformaters.py
aoc/solution.py
aoc/solution_manager.py
aoc/assets/__init__.py
aoc/assets/solution_template.txt
aoc/scripts/__init__.py
aoc/scripts/aoc.py
aoc_starter-0.2.0.dist-info/LICENSE
aoc_starter-0.2.0.dist-info/METADATA
aoc_starter-0.2.0.dist-info/WHEEL
aoc_starter-0.2.0.dist-info/entry_points.txt
aoc_starter-0.2.0.dist-info/top_level.txt
aoc_starter-0.2.0.dist-info/RECORD
