Metadata-Version: 2.1
Name: aoc-starter
Version: 0.2.0
Summary: "Framework for creating and testing solutions to the Advent of Code."
Home-page: https://github.com/mbmackenzie/advent-of-code-starter
Author: Matt Mackenzie
Author-email: mbm2228@columbia.edu
License: MIT
Platform: UNKNOWN
Classifier: License :: OSI Approved :: MIT License
Classifier: Programming Language :: Python :: 3
Classifier: Programming Language :: Python :: 3 :: Only
Classifier: Programming Language :: Python :: 3.9
Classifier: Programming Language :: Python :: 3.10
Classifier: Programming Language :: Python :: Implementation :: CPython
Requires-Python: >=3.9
License-File: LICENSE
Requires-Dist: click
